opencopilot/.dockerignore
opencopilot/__init__.py
opencopilot/analytics.py
opencopilot/app.py
opencopilot/application.py
opencopilot/callbacks.py
opencopilot/cli.py
opencopilot/exception_utils.py
opencopilot/oss.py
opencopilot/settings.py
opencopilot/__pycache__/__init__.cpython-310.pyc
opencopilot/__pycache__/__init__.cpython-38.pyc
opencopilot/__pycache__/__init__.cpython-39.pyc
opencopilot/__pycache__/analytics.cpython-310.pyc
opencopilot/__pycache__/app.cpython-310.pyc
opencopilot/__pycache__/app.cpython-39.pyc
opencopilot/__pycache__/application.cpython-310.pyc
opencopilot/__pycache__/application.cpython-38.pyc
opencopilot/__pycache__/application.cpython-39.pyc
opencopilot/__pycache__/callbacks.cpython-310.pyc
opencopilot/__pycache__/cli.cpython-310.pyc
opencopilot/__pycache__/exception_utils.cpython-310.pyc
opencopilot/__pycache__/oss.cpython-310.pyc
opencopilot/__pycache__/settings.cpython-310.pyc
opencopilot/__pycache__/settings.cpython-39.pyc
opencopilot/authorization/__init__.py
opencopilot/authorization/create_access_token.py
opencopilot/authorization/validate_api_key_use_case.py
opencopilot/authorization/__pycache__/__init__.cpython-310.pyc
opencopilot/authorization/__pycache__/create_access_token.cpython-310.pyc
opencopilot/authorization/__pycache__/validate_api_key_use_case.cpython-310.pyc
opencopilot/domain/__init__.py
opencopilot/domain/error_messages.py
opencopilot/domain/errors.py
opencopilot/domain/__pycache__/__init__.cpython-310.pyc
opencopilot/domain/__pycache__/error_messages.cpython-310.pyc
opencopilot/domain/__pycache__/errors.cpython-310.pyc
opencopilot/domain/chat/__init__.py
opencopilot/domain/chat/chat_conversations_use_case.py
opencopilot/domain/chat/chat_delete_use_case.py
opencopilot/domain/chat/entities.py
opencopilot/domain/chat/get_chat_history_use_case.py
opencopilot/domain/chat/get_token_count_use_case.py
opencopilot/domain/chat/is_user_allowed_to_chat_use_case.py
opencopilot/domain/chat/on_user_message_streaming_use_case.py
opencopilot_ai-0.3.8.dist-info/LICENCE.txt
opencopilot_ai-0.3.8.dist-info/METADATA
opencopilot_ai-0.3.8.dist-info/WHEEL
opencopilot_ai-0.3.8.dist-info/entry_points.txt
opencopilot_ai-0.3.8.dist-info/top_level.txt
opencopilot_ai-0.3.8.dist-info/RECORD
