Metadata-Version: 2.1
Name: opencopilot-ai
Version: 0.3.8
Summary: OpenCopilot Backend
Home-page: https://github.com/opencopilotdev/opencopilot
Author: OpenCopilot
Author-email: kaspar@nftport.xyz
License: MIT
License-File: LICENCE.txt
Requires-Dist: fastapi
Requires-Dist: dataclasses-json
Requires-Dist: python-dotenv
Requires-Dist: python-json-logger
Requires-Dist: uvicorn
Requires-Dist: pandas
Requires-Dist: pexpect
Requires-Dist: langchain >=0.0.217
Requires-Dist: passlib
Requires-Dist: pyjwt[crypto]
Requires-Dist: Jinja2
Requires-Dist: tiktoken
Requires-Dist: weaviate-client >=3.23.2
Requires-Dist: pypdf
Requires-Dist: unstructured
Requires-Dist: pdf2image
Requires-Dist: openai
Requires-Dist: xxhash
Requires-Dist: omegaconf
Requires-Dist: openpyxl
Requires-Dist: typer[all]
Requires-Dist: trafilatura
Requires-Dist: filetype
Requires-Dist: segment-analytics-python
Requires-Dist: psutil
Provides-Extra: llama
Requires-Dist: llama-cpp-python ==0.1.83 ; extra == 'llama'
